<?xml version="1.0" encoding="UTF-8"?>
<!DOCTYPE mapper PUBLIC "-//mybatis.org//DTD Mapper 3.0//EN" "http://mybatis.org/dtd/mybatis-3-mapper.dtd">
<mapper namespace="com.dao.MmSysUserOrdersMapper">
  <resultMap id="BaseResultMap" type="com.pojo.MmSysUserOrders">
    <!--
      WARNING - @mbggenerated
      This element is automatically generated by MyBatis Generator, do not modify.
      This element was generated on Sat Dec 29 21:21:51 CST 2018.
    -->
    <id column="id" jdbcType="INTEGER" property="id" />
    <result column="uid" jdbcType="INTEGER" property="uid" />
    <result column="oid" jdbcType="INTEGER" property="oid" />
    <result column="order_money" jdbcType="DOUBLE" property="orderMoney" />
    <result column="rebate_money" jdbcType="DOUBLE" property="rebateMoney" />
    <result column="flag" jdbcType="INTEGER" property="flag" />
    <result column="gznName" jdbcType="VARCHAR" property="gznname" />
    <result column="profits" jdbcType="DOUBLE" property="profits" />
    <result column="level1" jdbcType="DOUBLE" property="level1" />
    <result column="level2" jdbcType="DOUBLE" property="level2" />
    <result column="level3" jdbcType="DOUBLE" property="level3" />
    <result column="openId1" jdbcType="VARCHAR" property="openid1" />
    <result column="openId2" jdbcType="VARCHAR" property="openid2" />
    <result column="openId3" jdbcType="VARCHAR" property="openid3" />
  </resultMap>
  <sql id="Base_Column_List">
    <!--
      WARNING - @mbggenerated
      This element is automatically generated by MyBatis Generator, do not modify.
      This element was generated on Sat Dec 29 21:21:51 CST 2018.
    -->
    id, uid, oid, order_money, rebate_money, flag, gznName, profits, level1, level2, 
    level3, openId1, openId2, openId3
  </sql>
  <select id="selectByPrimaryKey" parameterType="java.lang.Integer" resultMap="BaseResultMap">
    <!--
      WARNING - @mbggenerated
      This element is automatically generated by MyBatis Generator, do not modify.
      This element was generated on Sat Dec 29 21:21:51 CST 2018.
    -->
    select 
    <include refid="Base_Column_List" />
    from mm_sys_user_orders
    where id = #{id,jdbcType=INTEGER}
  </select>
  <delete id="deleteByPrimaryKey" parameterType="java.lang.Integer">
    <!--
      WARNING - @mbggenerated
      This element is automatically generated by MyBatis Generator, do not modify.
      This element was generated on Sat Dec 29 21:21:51 CST 2018.
    -->
    delete from mm_sys_user_orders
    where id = #{id,jdbcType=INTEGER}
  </delete>
  <insert id="insert" parameterType="com.pojo.MmSysUserOrders">
    <!--
      WARNING - @mbggenerated
      This element is automatically generated by MyBatis Generator, do not modify.
      This element was generated on Sat Dec 29 21:21:51 CST 2018.
    -->
    insert into mm_sys_user_orders (id, uid, oid, 
      order_money, rebate_money, flag, 
      gznName, profits, level1, 
      level2, level3, openId1, 
      openId2, openId3)
    values (#{id,jdbcType=INTEGER}, #{uid,jdbcType=INTEGER}, #{oid,jdbcType=INTEGER}, 
      #{orderMoney,jdbcType=DOUBLE}, #{rebateMoney,jdbcType=DOUBLE}, #{flag,jdbcType=INTEGER}, 
      #{gznname,jdbcType=VARCHAR}, #{profits,jdbcType=DOUBLE}, #{level1,jdbcType=DOUBLE}, 
      #{level2,jdbcType=DOUBLE}, #{level3,jdbcType=DOUBLE}, #{openid1,jdbcType=VARCHAR}, 
      #{openid2,jdbcType=VARCHAR}, #{openid3,jdbcType=VARCHAR})
  </insert>
  <insert id="insertSelective" parameterType="com.pojo.MmSysUserOrders">
    <!--
      WARNING - @mbggenerated
      This element is automatically generated by MyBatis Generator, do not modify.
      This element was generated on Sat Dec 29 21:21:51 CST 2018.
    -->
    insert into mm_sys_user_orders
    <trim prefix="(" suffix=")" suffixOverrides=",">
      <if test="id != null">
        id,
      </if>
      <if test="uid != null">
        uid,
      </if>
      <if test="oid != null">
        oid,
      </if>
      <if test="orderMoney != null">
        order_money,
      </if>
      <if test="rebateMoney != null">
        rebate_money,
      </if>
      <if test="flag != null">
        flag,
      </if>
      <if test="gznname != null">
        gznName,
      </if>
      <if test="profits != null">
        profits,
      </if>
      <if test="level1 != null">
        level1,
      </if>
      <if test="level2 != null">
        level2,
      </if>
      <if test="level3 != null">
        level3,
      </if>
      <if test="openid1 != null">
        openId1,
      </if>
      <if test="openid2 != null">
        openId2,
      </if>
      <if test="openid3 != null">
        openId3,
      </if>
    </trim>
    <trim prefix="values (" suffix=")" suffixOverrides=",">
      <if test="id != null">
        #{id,jdbcType=INTEGER},
      </if>
      <if test="uid != null">
        #{uid,jdbcType=INTEGER},
      </if>
      <if test="oid != null">
        #{oid,jdbcType=INTEGER},
      </if>
      <if test="orderMoney != null">
        #{orderMoney,jdbcType=DOUBLE},
      </if>
      <if test="rebateMoney != null">
        #{rebateMoney,jdbcType=DOUBLE},
      </if>
      <if test="flag != null">
        #{flag,jdbcType=INTEGER},
      </if>
      <if test="gznname != null">
        #{gznname,jdbcType=VARCHAR},
      </if>
      <if test="profits != null">
        #{profits,jdbcType=DOUBLE},
      </if>
      <if test="level1 != null">
        #{level1,jdbcType=DOUBLE},
      </if>
      <if test="level2 != null">
        #{level2,jdbcType=DOUBLE},
      </if>
      <if test="level3 != null">
        #{level3,jdbcType=DOUBLE},
      </if>
      <if test="openid1 != null">
        #{openid1,jdbcType=VARCHAR},
      </if>
      <if test="openid2 != null">
        #{openid2,jdbcType=VARCHAR},
      </if>
      <if test="openid3 != null">
        #{openid3,jdbcType=VARCHAR},
      </if>
    </trim>
  </insert>
  <update id="updateByPrimaryKeySelective" parameterType="com.pojo.MmSysUserOrders">
    <!--
      WARNING - @mbggenerated
      This element is automatically generated by MyBatis Generator, do not modify.
      This element was generated on Sat Dec 29 21:21:51 CST 2018.
    -->
    update mm_sys_user_orders
    <set>
      <if test="uid != null">
        uid = #{uid,jdbcType=INTEGER},
      </if>
      <if test="oid != null">
        oid = #{oid,jdbcType=INTEGER},
      </if>
      <if test="orderMoney != null">
        order_money = #{orderMoney,jdbcType=DOUBLE},
      </if>
      <if test="rebateMoney != null">
        rebate_money = #{rebateMoney,jdbcType=DOUBLE},
      </if>
      <if test="flag != null">
        flag = #{flag,jdbcType=INTEGER},
      </if>
      <if test="gznname != null">
        gznName = #{gznname,jdbcType=VARCHAR},
      </if>
      <if test="profits != null">
        profits = #{profits,jdbcType=DOUBLE},
      </if>
      <if test="level1 != null">
        level1 = #{level1,jdbcType=DOUBLE},
      </if>
      <if test="level2 != null">
        level2 = #{level2,jdbcType=DOUBLE},
      </if>
      <if test="level3 != null">
        level3 = #{level3,jdbcType=DOUBLE},
      </if>
      <if test="openid1 != null">
        openId1 = #{openid1,jdbcType=VARCHAR},
      </if>
      <if test="openid2 != null">
        openId2 = #{openid2,jdbcType=VARCHAR},
      </if>
      <if test="openid3 != null">
        openId3 = #{openid3,jdbcType=VARCHAR},
      </if>
    </set>
    where id = #{id,jdbcType=INTEGER}
  </update>
  <update id="updateByPrimaryKey" parameterType="com.pojo.MmSysUserOrders">
    <!--
      WARNING - @mbggenerated
      This element is automatically generated by MyBatis Generator, do not modify.
      This element was generated on Sat Dec 29 21:21:51 CST 2018.
    -->
    update mm_sys_user_orders
    set uid = #{uid,jdbcType=INTEGER},
      oid = #{oid,jdbcType=INTEGER},
      order_money = #{orderMoney,jdbcType=DOUBLE},
      rebate_money = #{rebateMoney,jdbcType=DOUBLE},
      flag = #{flag,jdbcType=INTEGER},
      gznName = #{gznname,jdbcType=VARCHAR},
      profits = #{profits,jdbcType=DOUBLE},
      level1 = #{level1,jdbcType=DOUBLE},
      level2 = #{level2,jdbcType=DOUBLE},
      level3 = #{level3,jdbcType=DOUBLE},
      openId1 = #{openid1,jdbcType=VARCHAR},
      openId2 = #{openid2,jdbcType=VARCHAR},
      openId3 = #{openid3,jdbcType=VARCHAR}
    where id = #{id,jdbcType=INTEGER}
  </update>



  <select id="selectFlag0ByUserId" parameterType="java.lang.Integer" resultType="java.lang.Double">
    select IFNULL(sum(rebate_money),0)
    from mm_sys_user_orders where uid = #{uid} and flag = 0
  </select>
  <select id="selectFlag3ByUserId" parameterType="java.lang.Integer" resultType="java.lang.Double">
    select IFNULL(sum(rebate_money),0)
    from mm_sys_user_orders where uid = #{uid} and flag = 3
  </select>
</mapper>